fakemessages/__init__.py
fakemessages/apps.py
fakemessages/management/__init__.py
fakemessages/management/commands/__init__.py
fakemessages/management/commands/fakemessages.py
django_fakemessages-0.0.1.dist-info/LICENSE
django_fakemessages-0.0.1.dist-info/WHEEL
django_fakemessages-0.0.1.dist-info/METADATA
django_fakemessages-0.0.1.dist-info/RECORD
