Metadata-Version: 2.1
Name: django-fakemessages
Version: 0.0.1
Summary: Generate fake language files
Home-page: https://github.com/pfouque/django-fakemessages
License: MIT
Author: Pascal Fouque
Author-email: fouquepascal@gmail.com
Maintainer: Pascal Fouque
Maintainer-email: fouquepascal@gmail.com
Requires-Python: >=3.8,<4.0
Classifier: Development Status :: 1 - Planning
Classifier: Environment :: Web Environment
Classifier: Framework :: Django
Classifier: Framework :: Django :: 3.2
Classifier: Framework :: Django :: 4
Classifier: Framework :: Django :: 4.0
Classifier: Framework :: Django :: 4.1
Classifier: License :: OSI Approved :: MIT License
Classifier: Operating System :: OS Independent
Classifier: Programming Language :: Python :: 3
Classifier: Programming Language :: Python :: 3.8
Classifier: Programming Language :: Python :: 3.9
Classifier: Programming Language :: Python :: 3.10
Classifier: Programming Language :: Python :: 3.11
Classifier: Programming Language :: Python :: 3 :: Only
Classifier: Programming Language :: Python :: 3.10
Classifier: Programming Language :: Python :: 3.11
Classifier: Programming Language :: Python :: 3.8
Classifier: Programming Language :: Python :: 3.9
Requires-Dist: django (>=3.2,<5.0)
Requires-Dist: translate-toolkit (>=3.8.5,<4.0.0)
Project-URL: Documentation, https://github.com/pfouque/django-fakemessages
Project-URL: Repository, https://github.com/pfouque/django-fakemessages
